azure/monitor/opentelemetry/distro/configurator.py
azure/monitor/opentelemetry/distro/distro.py
azure/monitor/opentelemetry/distro/version.py
azure_monitor_opentelemetry_distro-1.0.0b9.dist-info/METADATA
azure_monitor_opentelemetry_distro-1.0.0b9.dist-info/WHEEL
azure_monitor_opentelemetry_distro-1.0.0b9.dist-info/entry_points.txt
azure_monitor_opentelemetry_distro-1.0.0b9.dist-info/top_level.txt
azure_monitor_opentelemetry_distro-1.0.0b9.dist-info/RECORD
