Metadata-Version: 2.1
Name: azure-monitor-opentelemetry-distro
Version: 1.0.0b9
Summary: Azure Monitor Distro for OpenTelemetry Python
Home-page: https://github.com/microsoft/ApplicationInsights-Python
Author: Microsoft Corporation
License: MIT License
Platform: any
Classifier: Development Status :: 4 - Beta
Classifier: Programming Language :: Python
Classifier: Programming Language :: Python :: 3
Classifier: Programming Language :: Python :: 3.7
Classifier: Programming Language :: Python :: 3.8
Classifier: Programming Language :: Python :: 3.9
Classifier: Programming Language :: Python :: 3.10
Classifier: License :: OSI Approved :: MIT License
Classifier: Typing :: Typed
Requires-Python: >=3.7
Requires-Dist: azure-monitor-opentelemetry-exporter (==1.0.0b8)
Requires-Dist: opentelemetry-instrumentation (~=0.33b0)
Requires-Dist: opentelemetry-instrumentation-requests (~=0.33b0)
Requires-Dist: opentelemetry-instrumentation-flask (~=0.33b0)
Requires-Dist: opentelemetry-instrumentation-psycopg2 (~=0.33b0)
